uasgi/__init__.py
uasgi/__main__.py
uasgi/arbiter.py
uasgi/cli.py
uasgi/config.py
uasgi/lifespan.py
uasgi/main.py
uasgi/protocol.py
uasgi/reloader.py
uasgi/server.py
uasgi/uhttp.py
uasgi/utils.py
uasgi/worker.py
uasgi-0.4.0.dist-info/licenses/LICENSE
uasgi-0.4.0.dist-info/METADATA
uasgi-0.4.0.dist-info/WHEEL
uasgi-0.4.0.dist-info/top_level.txt
uasgi-0.4.0.dist-info/RECORD
