Metadata-Version: 2.4
Name: uasgi
Version: 0.4.0
Summary: uASGI: A High-Performance ASGI Web Server
Classifier: Programming Language :: Python :: 3
Classifier: Programming Language :: Python :: 3.10
Classifier: License :: OSI Approved :: MIT License
Classifier: Operating System :: OS Independent
Classifier: Topic :: Internet :: WWW/HTTP :: WSGI :: Server
Classifier: Framework :: AsyncIO
Requires-Python: >=3.10
License-File: LICENSE
Requires-Dist: click>=8.2.1
Requires-Dist: httptools>=0.6.4
Requires-Dist: uvloop>=0.21.0
Requires-Dist: watchdog>=6.0.0
Dynamic: license-file
